sonictag/__init__.py
sonictag/data.py
sonictag/logger.py
sonictag/ofdm.py
sonictag/steganography.py
sonictag/sync.py
sonictag/transceiver.py
sonictag-0.2.0.dist-info/METADATA
sonictag-0.2.0.dist-info/WHEEL
sonictag-0.2.0.dist-info/licenses/LICENSE
sonictag-0.2.0.dist-info/RECORD
