Metadata-Version: 2.4
Name: sonictag
Version: 0.2.0
Summary: Ultrasonic data transmission package using OFDM and Reed-Solomon ECC
Project-URL: Homepage, https://github.com/jillou35/SonicTag
Project-URL: Repository, https://github.com/jillou35/SonicTag
Project-URL: Issues, https://github.com/jillou35/SonicTag/issues
Author-email: Jillian Strenk <jillian.strenk@posteo.net>
License-Expression: MIT
License-File: LICENSE
Classifier: Operating System :: OS Independent
Classifier: Programming Language :: Python :: 3
Requires-Python: >=3.10
Requires-Dist: numpy
Requires-Dist: reedsolo
Requires-Dist: scipy
Requires-Dist: scipy-stubs
Requires-Dist: sounddevice
Requires-Dist: soundfile
